{"id": "9221451844","server": "3756","farm": "4","userId": "28313305@N08","secret": "2409c33a6b","title": "balcony view","loc": {"type": "Point","coordinates": [103.80886,1.271837]}} 
{"id": "9087637675","server": "3780","farm": "4","userId": "96364464@N05","secret": "971939bc27","title": "Going on train ride to the student care.","loc": {"type": "Point","coordinates": [103.8073,1.271806]}} 
{"id": "9005533502","server": "3701","farm": "4","userId": "82747221@N04","secret": "0cdd852d82","title": "Saw a monkey on the way to the mrt LOL","loc": {"type": "Point","coordinates": [103.80966,1.270629]}} 
{"id": "8352812255","server": "8369","farm": "9","userId": "79022843@N00","secret": "ff38470fdf","title": "View on CTE and Vivo City from the cable car","loc": {"type": "Point","coordinates": [103.80686,1.271509]}} 
