{"id": "8891766187","server": "3704","farm": "4","userId": "24356987@N08","secret": "b1de8b359e","title": "Baya Weaver","loc": {"type": "Point","coordinates": [103.706505,1.419762]}} 
{"id": "8396314473","server": "8193","farm": "9","userId": "21596674@N00","secret": "35453be49c","title": "Warm Banana Bread with Vanila Ice Cream topped with Gula Melaka.","loc": {"type": "Point","coordinates": [103.71648,1.418593]}} 
{"id": "8352941352","server": "8324","farm": "9","userId": "48889054224@N01","secret": "9568199538","title": "Worth the long (by SG standards) drive out.","loc": {"type": "Point","coordinates": [103.71648,1.418593]}} 
