{"id": "8494137925","server": "8386","farm": "9","userId": "14932126@N08","secret": "942075557d","title": "","loc": {"type": "Point","coordinates": [103.773834,1.357333]}} 
{"id": "9276770638","server": "3759","farm": "4","userId": "37631879@N03","secret": "3bf9d9a8b8","title": "All the single ladies .....","loc": {"type": "Point","coordinates": [103.77375,1.360651]}} 
{"id": "9253507358","server": "5451","farm": "6","userId": "51489026@N02","secret": "77333f816b","title": "The peak","loc": {"type": "Point","coordinates": [103.77638,1.354582]}} 
{"id": "9243316953","server": "2844","farm": "3","userId": "51489026@N02","secret": "296809a050","title": "The man in red short","loc": {"type": "Point","coordinates": [103.77668,1.354754]}} 
{"id": "9232576472","server": "7321","farm": "8","userId": "12997609@N00","secret": "528b431e83","title": "IMG_7445","loc": {"type": "Point","coordinates": [103.77635,1.354858]}} 
{"id": "9232602278","server": "3764","farm": "4","userId": "12997609@N00","secret": "42af5db98c","title": "IMG_7448","loc": {"type": "Point","coordinates": [103.77505,1.354952]}} 
{"id": "9218957859","server": "3740","farm": "4","userId": "13394179@N06","secret": "5e5d6dacc9","title": "IMAG0235","loc": {"type": "Point","coordinates": [103.77723,1.360486]}} 
{"id": "9218950315","server": "2894","farm": "3","userId": "13394179@N06","secret": "8f68c00f15","title": "IMAG0233","loc": {"type": "Point","coordinates": [103.77723,1.360352]}} 
{"id": "9209109784","server": "2830","farm": "3","userId": "30908892@N08","secret": "f21e700cf9","title": "IMG_4054","loc": {"type": "Point","coordinates": [103.771835,1.356833]}} 
{"id": "9209110624","server": "7382","farm": "8","userId": "30908892@N08","secret": "f97fb26181","title": "IMG_4053","loc": {"type": "Point","coordinates": [103.771835,1.356833]}} 
{"id": "9173330759","server": "7448","farm": "8","userId": "30908892@N08","secret": "3439cf2b81","title": "IMG_4058","loc": {"type": "Point","coordinates": [103.7735,1.357166]}} 
{"id": "8709748798","server": "8115","farm": "9","userId": "51035533573@N01","secret": "8974468849","title": "#jungle #nature #bukittimah #Reservoir #singapore","loc": {"type": "Point","coordinates": [103.77668,1.354754]}} 
{"id": "8706069343","server": "8558","farm": "9","userId": "79415820@N08","secret": "1b328ee586","title": "upload","loc": {"type": "Point","coordinates": [103.77179,1.356856]}} 
{"id": "8707181884","server": "8404","farm": "9","userId": "79415820@N08","secret": "49a31a6a84","title": "Away from the city, away from people.","loc": {"type": "Point","coordinates": [103.77179,1.356856]}} 
{"id": "8677391729","server": "8401","farm": "9","userId": "56560474@N04","secret": "57ef50579c","title": "IMG_20130406_181343","loc": {"type": "Point","coordinates": [103.7762,1.35465]}} 
{"id": "8677385351","server": "8402","farm": "9","userId": "56560474@N04","secret": "7a7e6356f7","title": "IMG_20130406_175310","loc": {"type": "Point","coordinates": [103.776474,1.354683]}} 
{"id": "8678483216","server": "8400","farm": "9","userId": "56560474@N04","secret": "4697d8a08a","title": "IMG_20130406_174044","loc": {"type": "Point","coordinates": [103.7765,1.354683]}} 
{"id": "8678478188","server": "8381","farm": "9","userId": "56560474@N04","secret": "1af9de4466","title": "IMG_20130406_174023","loc": {"type": "Point","coordinates": [103.77664,1.354322]}} 
{"id": "8678485602","server": "8396","farm": "9","userId": "56560474@N04","secret": "b7bfcb5d2f","title": "IMG_20130406_174102","loc": {"type": "Point","coordinates": [103.776474,1.354694]}} 
{"id": "8678488194","server": "8262","farm": "9","userId": "56560474@N04","secret": "8c93f6ce1c","title": "IMG_20130406_174120","loc": {"type": "Point","coordinates": [103.77646,1.354691]}} 
{"id": "8678480564","server": "8390","farm": "9","userId": "56560474@N04","secret": "ec54ba4772","title": "IMG_20130406_174035","loc": {"type": "Point","coordinates": [103.776474,1.35468]}} 
{"id": "8677387725","server": "8122","farm": "9","userId": "56560474@N04","secret": "814a76f8d4","title": "IMG_20130406_175312","loc": {"type": "Point","coordinates": [103.776474,1.354683]}} 
{"id": "8677365747","server": "8383","farm": "9","userId": "56560474@N04","secret": "848e145b84","title": "IMG_20130406_173559","loc": {"type": "Point","coordinates": [103.77646,1.354655]}} 
{"id": "8677367993","server": "8257","farm": "9","userId": "56560474@N04","secret": "c97b62c6c6","title": "IMG_20130406_173628","loc": {"type": "Point","coordinates": [103.77649,1.354675]}} 
{"id": "8677370441","server": "8532","farm": "9","userId": "56560474@N04","secret": "d02c8b1ed3","title": "IMG_20130406_174021","loc": {"type": "Point","coordinates": [103.77664,1.354322]}} 
{"id": "8645820076","server": "8394","farm": "9","userId": "94860988@N03","secret": "6036148c17","title": "IMG_2405","loc": {"type": "Point","coordinates": [103.77752,1.354518]}} 
{"id": "8590822127","server": "8098","farm": "9","userId": "7311038@N03","secret": "699b3cce42","title": "W08 – Paths – Project #13-52","loc": {"type": "Point","coordinates": [103.77612,1.354583]}} 
{"id": "8585476280","server": "8240","farm": "9","userId": "7310714@N06","secret": "cdf1fa48a9","title": "","loc": {"type": "Point","coordinates": [103.776665,1.3545]}} 
{"id": "8585477424","server": "8386","farm": "9","userId": "7310714@N06","secret": "89ec8d6df3","title": "","loc": {"type": "Point","coordinates": [103.77634,1.354666]}} 
{"id": "8584204935","server": "8227","farm": "9","userId": "15170730@N07","secret": "fb6a61006b","title": "action","loc": {"type": "Point","coordinates": [103.77668,1.354754]}} 
{"id": "8580713571","server": "8515","farm": "9","userId": "15170730@N07","secret": "08afc55fd1","title": "climb!","loc": {"type": "Point","coordinates": [103.77668,1.354754]}} 
{"id": "8564178939","server": "8228","farm": "9","userId": "55486190@N00","secret": "004b51431a","title": "Climbing up lots of #stairs to train for #MountKK at #BukitTimahHill","loc": {"type": "Point","coordinates": [103.7745,1.36]}} 
{"id": "8565284480","server": "8368","farm": "9","userId": "55486190@N00","secret": "0ea0023f6e","title": "#BukitTimahHill will be our #training ground all the way to June 2013","loc": {"type": "Point","coordinates": [103.77668,1.354754]}} 
{"id": "8565034138","server": "8095","farm": "9","userId": "55486190@N00","secret": "6faa6af2cc","title": "Dr Jason Yap's #CEFC #CYAN Mentor Group at #BukitTimahHill Summit","loc": {"type": "Point","coordinates": [103.7764,1.354625]}} 
{"id": "8564971452","server": "8523","farm": "9","userId": "55486190@N00","secret": "94a58c71d0","title": "Ai showing #CEFC #CYAN Mentor Group some stretching #exercises","loc": {"type": "Point","coordinates": [103.7764,1.354625]}} 
{"id": "8563753853","server": "8385","farm": "9","userId": "55486190@N00","secret": "2f21b945f3","title": "#CEFC #CYAN Mentor Group #BukitTimahHill training at North View Path","loc": {"type": "Point","coordinates": [103.7745,1.36]}} 
{"id": "8541269550","server": "8380","farm": "9","userId": "55486190@N00","secret": "66495548cc","title": "Jason, Ai & YC after #BukitTimahHill training at the #Summit","loc": {"type": "Point","coordinates": [103.7764,1.354625]}} 
{"id": "8540121863","server": "8370","farm": "9","userId": "55486190@N00","secret": "0109c03eb9","title": "Ps Barney praying and briefing #CEFC #CYAN #MtKK climbers","loc": {"type": "Point","coordinates": [103.7764,1.354625]}} 
{"id": "8541036398","server": "8110","farm": "9","userId": "55486190@N00","secret": "2975568f09","title": "Jason & YC on #BukitTimahHill training with #CEFC #CYAN","loc": {"type": "Point","coordinates": [103.782005,1.356513]}} 
{"id": "8500721906","server": "8096","farm": "9","userId": "14932126@N08","secret": "119b676167","title": "IMG_0115","loc": {"type": "Point","coordinates": [103.773834,1.357333]}} 
{"id": "8499617697","server": "8235","farm": "9","userId": "14932126@N08","secret": "67234784ff","title": "IMG_0116","loc": {"type": "Point","coordinates": [103.773834,1.357333]}} 
{"id": "8499614381","server": "8523","farm": "9","userId": "14932126@N08","secret": "77f3d40349","title": "IMG_0114","loc": {"type": "Point","coordinates": [103.773834,1.357333]}} 
{"id": "8500724528","server": "8529","farm": "9","userId": "14932126@N08","secret": "b4b921243d","title": "IMG_0117","loc": {"type": "Point","coordinates": [103.77683,1.3545]}} 
{"id": "8499613653","server": "8369","farm": "9","userId": "14932126@N08","secret": "0e24a8eda1","title": "IMG_0113","loc": {"type": "Point","coordinates": [103.774,1.357333]}} 
{"id": "8500718194","server": "8112","farm": "9","userId": "14932126@N08","secret": "0cf8434fa3","title": "IMG_0112","loc": {"type": "Point","coordinates": [103.774,1.357333]}} 
{"id": "8494134799","server": "8251","farm": "9","userId": "14932126@N08","secret": "8a4a6802d8","title": "","loc": {"type": "Point","coordinates": [103.774,1.357333]}} 
{"id": "8494136523","server": "8381","farm": "9","userId": "14932126@N08","secret": "02afaf464a","title": "","loc": {"type": "Point","coordinates": [103.773834,1.357333]}} 
{"id": "8495238028","server": "8090","farm": "9","userId": "14932126@N08","secret": "00ed52bbb4","title": "","loc": {"type": "Point","coordinates": [103.77683,1.3545]}} 
{"id": "8495235152","server": "8511","farm": "9","userId": "14932126@N08","secret": "1f5103735c","title": "","loc": {"type": "Point","coordinates": [103.774,1.357333]}} 
{"id": "8419462947","server": "8227","farm": "9","userId": "51192515@N00","secret": "673bc53808","title": "DSC07307","loc": {"type": "Point","coordinates": [103.77644,1.354683]}} 
{"id": "8419469817","server": "8075","farm": "9","userId": "51192515@N00","secret": "c68692f7bd","title": "DSC07306","loc": {"type": "Point","coordinates": [103.77644,1.354661]}} 
{"id": "8420594358","server": "8211","farm": "9","userId": "51192515@N00","secret": "0313688f01","title": "DSC07302","loc": {"type": "Point","coordinates": [103.7764,1.354697]}} 
{"id": "8377212524","server": "8364","farm": "9","userId": "7686890@N05","secret": "a0d468054c","title": "Bukit Timah nature reserve","loc": {"type": "Point","coordinates": [103.77639,1.354794]}} 
{"id": "8375123061","server": "8498","farm": "9","userId": "7686890@N05","secret": "95f388890c","title": "Bukit Timah nature reserve","loc": {"type": "Point","coordinates": [103.77639,1.354794]}} 
{"id": "8376196210","server": "8195","farm": "9","userId": "7686890@N05","secret": "18dd3a0b50","title": "Bukit Timah nature reserve","loc": {"type": "Point","coordinates": [103.77639,1.354794]}} 
{"id": "8287020648","server": "8076","farm": "9","userId": "10009200@N04","secret": "353e56dbb7","title": "","loc": {"type": "Point","coordinates": [103.77669,1.354754]}} 
{"id": "8199174784","server": "8347","farm": "9","userId": "58438099@N04","secret": "095a2dc25a","title": "Washout!","loc": {"type": "Point","coordinates": [103.77836,1.360696]}} 
{"id": "8199182384","server": "8484","farm": "9","userId": "58438099@N04","secret": "da1138d3c8","title": "Parasitic fig. #WPHtakeahike","loc": {"type": "Point","coordinates": [103.77836,1.360696]}} 
{"id": "8199171822","server": "8346","farm": "9","userId": "58438099@N04","secret": "6db6204bd3","title": "Termite colony on the move under a heavy rain storm.","loc": {"type": "Point","coordinates": [103.77836,1.360696]}} 
{"id": "8062791931","server": "8457","farm": "9","userId": "99942665@N00","secret": "131ba88db3","title": "P1150255","loc": {"type": "Point","coordinates": [103.77702,1.360323]}} 
{"id": "8062795490","server": "8176","farm": "9","userId": "99942665@N00","secret": "4e673c4845","title": "P1150263","loc": {"type": "Point","coordinates": [103.77671,1.359035]}} 
{"id": "8062801902","server": "8173","farm": "9","userId": "99942665@N00","secret": "d67033aca2","title": "P1150280","loc": {"type": "Point","coordinates": [103.779724,1.354886]}} 
{"id": "8062795811","server": "8180","farm": "9","userId": "99942665@N00","secret": "b01a91ffc5","title": "P1150264","loc": {"type": "Point","coordinates": [103.77671,1.359035]}} 
{"id": "8062798334","server": "8039","farm": "9","userId": "99942665@N00","secret": "1ab7f04a8d","title": "P1150275","loc": {"type": "Point","coordinates": [103.779724,1.354886]}} 
{"id": "8062796887","server": "8031","farm": "9","userId": "99942665@N00","secret": "19bbc4357a","title": "P1150274","loc": {"type": "Point","coordinates": [103.779724,1.354886]}} 
{"id": "8062793541","server": "8173","farm": "9","userId": "99942665@N00","secret": "4d25754c9a","title": "P1150262","loc": {"type": "Point","coordinates": [103.77671,1.359035]}} 
{"id": "8062799282","server": "8457","farm": "9","userId": "99942665@N00","secret": "fefea3fa11","title": "P1150276","loc": {"type": "Point","coordinates": [103.779724,1.354886]}} 
{"id": "8062800310","server": "8031","farm": "9","userId": "99942665@N00","secret": "598beff9b3","title": "P1150279","loc": {"type": "Point","coordinates": [103.779724,1.354886]}} 
{"id": "8062793166","server": "8176","farm": "9","userId": "99942665@N00","secret": "c2d094682e","title": "P1150258","loc": {"type": "Point","coordinates": [103.77702,1.360323]}} 
{"id": "8062779556","server": "8460","farm": "9","userId": "99942665@N00","secret": "ac41c9e80c","title": "highres_166421542","loc": {"type": "Point","coordinates": [103.77256,1.361023]}} 
{"id": "8062761657","server": "8321","farm": "9","userId": "99942665@N00","secret": "e6d2c2d1b3","title": "P1150127","loc": {"type": "Point","coordinates": [103.77181,1.356885]}} 
{"id": "8062764233","server": "8452","farm": "9","userId": "99942665@N00","secret": "c6df385bc7","title": "P1150129","loc": {"type": "Point","coordinates": [103.77181,1.356885]}} 
{"id": "8062762393","server": "8169","farm": "9","userId": "99942665@N00","secret": "53bee45e83","title": "PANO_20121007_075411","loc": {"type": "Point","coordinates": [103.77181,1.356885]}} 
{"id": "8062765180","server": "8460","farm": "9","userId": "99942665@N00","secret": "2b7812538c","title": "P1150138","loc": {"type": "Point","coordinates": [103.77181,1.356885]}} 
{"id": "8035709046","server": "8175","farm": "9","userId": "22256257@N00","secret": "3e695d3a09","title": "Rain forest hiking","loc": {"type": "Point","coordinates": [103.77668,1.354754]}} 
{"id": "8035524309","server": "8037","farm": "9","userId": "22256257@N00","secret": "8a2017107a","title": "We don't have these critters back home.","loc": {"type": "Point","coordinates": [103.77668,1.354754]}} 
