{"id": "8246257426","server": "8059","farm": "9","userId": "66358983@N07","secret": "465d3985ef","title": "Family of Macaques","loc": {"type": "Point","coordinates": [103.803665,1.397166]}} 
{"id": "9330262127","server": "3792","farm": "4","userId": "54048808@N00","secret": "f5c9aa3b3c","title": "Red leaf in the sun.","loc": {"type": "Point","coordinates": [103.795334,1.402]}} 
{"id": "9326326470","server": "7315","farm": "8","userId": "66358983@N07","secret": "dbb18862a6","title": "Seletar Resevoir Singapore","loc": {"type": "Point","coordinates": [103.80268,1.397266]}} 
{"id": "9303741831","server": "7442","farm": "8","userId": "96738935@N00","secret": "bf94cae979","title": "IMG_1488","loc": {"type": "Point","coordinates": [103.7955,1.402]}} 
{"id": "9303741725","server": "2881","farm": "3","userId": "96738935@N00","secret": "c417210ca5","title": "IMG_1489","loc": {"type": "Point","coordinates": [103.7955,1.402]}} 
{"id": "9302400531","server": "3800","farm": "4","userId": "96738935@N00","secret": "8a73e2d34c","title": "IMG_0893","loc": {"type": "Point","coordinates": [103.795,1.401833]}} 
{"id": "9302400477","server": "2819","farm": "3","userId": "96738935@N00","secret": "b3b9fe3c40","title": "IMG_0894","loc": {"type": "Point","coordinates": [103.795,1.401833]}} 
{"id": "9302399877","server": "3778","farm": "4","userId": "96738935@N00","secret": "c7a22b652a","title": "IMG_0896","loc": {"type": "Point","coordinates": [103.794,1.402]}} 
{"id": "9302400317","server": "2867","farm": "3","userId": "96738935@N00","secret": "d49885b71b","title": "IMG_0895","loc": {"type": "Point","coordinates": [103.794,1.402]}} 
{"id": "9302415481","server": "7389","farm": "8","userId": "96738935@N00","secret": "c1086a30d3","title": "IMG_0836","loc": {"type": "Point","coordinates": [103.7955,1.402]}} 
{"id": "9305202090","server": "7283","farm": "8","userId": "96738935@N00","secret": "2d03bb2fa2","title": "IMG_0818","loc": {"type": "Point","coordinates": [103.795,1.402]}} 
{"id": "9302417229","server": "3692","farm": "4","userId": "96738935@N00","secret": "df82e08b44","title": "IMG_0831","loc": {"type": "Point","coordinates": [103.795334,1.401833]}} 
{"id": "9305195630","server": "7306","farm": "8","userId": "96738935@N00","secret": "67d2db0621","title": "IMG_0839","loc": {"type": "Point","coordinates": [103.7955,1.401833]}} 
{"id": "9302421593","server": "5473","farm": "6","userId": "96738935@N00","secret": "aa08dc574e","title": "IMG_0816","loc": {"type": "Point","coordinates": [103.79483,1.401833]}} 
{"id": "9305197972","server": "2888","farm": "3","userId": "96738935@N00","secret": "a6e8865873","title": "IMG_0832","loc": {"type": "Point","coordinates": [103.795334,1.402]}} 
{"id": "9302422995","server": "5534","farm": "6","userId": "96738935@N00","secret": "04e4aa7eec","title": "IMG_0812","loc": {"type": "Point","coordinates": [103.794,1.4015]}} 
{"id": "9302422313","server": "5511","farm": "6","userId": "96738935@N00","secret": "b2cedf3cba","title": "IMG_0814","loc": {"type": "Point","coordinates": [103.79417,1.4015]}} 
{"id": "9302420661","server": "7369","farm": "8","userId": "96738935@N00","secret": "ff2148b3f1","title": "IMG_0819","loc": {"type": "Point","coordinates": [103.79483,1.402]}} 
{"id": "9302416529","server": "3671","farm": "4","userId": "96738935@N00","secret": "ef3656e601","title": "IMG_0833","loc": {"type": "Point","coordinates": [103.795334,1.402]}} 
{"id": "9302416143","server": "2884","farm": "3","userId": "96738935@N00","secret": "2c22cacae8","title": "IMG_0834","loc": {"type": "Point","coordinates": [103.795334,1.402]}} 
{"id": "9302413619","server": "2833","farm": "3","userId": "96738935@N00","secret": "c9286871ff","title": "IMG_0842","loc": {"type": "Point","coordinates": [103.79583,1.402]}} 
{"id": "9302421933","server": "7397","farm": "8","userId": "96738935@N00","secret": "8ac191d283","title": "IMG_0815","loc": {"type": "Point","coordinates": [103.79417,1.4015]}} 
{"id": "9302417537","server": "3763","farm": "4","userId": "96738935@N00","secret": "69b3355b11","title": "IMG_0830","loc": {"type": "Point","coordinates": [103.795,1.401666]}} 
{"id": "9302413929","server": "7448","farm": "8","userId": "96738935@N00","secret": "a09d44d793","title": "IMG_0841","loc": {"type": "Point","coordinates": [103.79583,1.402]}} 
{"id": "9305196284","server": "3669","farm": "4","userId": "96738935@N00","secret": "87b152ea8d","title": "IMG_0837","loc": {"type": "Point","coordinates": [103.795334,1.402]}} 
{"id": "9305202418","server": "2837","farm": "3","userId": "96738935@N00","secret": "07e9816db3","title": "IMG_0817","loc": {"type": "Point","coordinates": [103.79466,1.402]}} 
{"id": "9302414771","server": "2824","farm": "3","userId": "96738935@N00","secret": "141c578660","title": "IMG_0838","loc": {"type": "Point","coordinates": [103.7955,1.402]}} 
{"id": "9302414193","server": "7349","farm": "8","userId": "96738935@N00","secret": "6c39fbf66c","title": "IMG_0840","loc": {"type": "Point","coordinates": [103.7955,1.401833]}} 
{"id": "9305196928","server": "5348","farm": "6","userId": "96738935@N00","secret": "c87e2d07b4","title": "IMG_0835","loc": {"type": "Point","coordinates": [103.7955,1.402]}} 
{"id": "9302422641","server": "5442","farm": "6","userId": "96738935@N00","secret": "4c09fc9496","title": "IMG_0813","loc": {"type": "Point","coordinates": [103.794,1.4015]}} 
{"id": "9302238069","server": "7378","farm": "8","userId": "96738935@N00","secret": "a7edfe5ff0","title": "IMG_0809","loc": {"type": "Point","coordinates": [103.79383,1.402166]}} 
{"id": "9302231141","server": "3813","farm": "4","userId": "96738935@N00","secret": "587b6d0eab","title": "IMG_0811","loc": {"type": "Point","coordinates": [103.794,1.402]}} 
{"id": "9302237763","server": "3783","farm": "4","userId": "96738935@N00","secret": "75165e359b","title": "IMG_0810","loc": {"type": "Point","coordinates": [103.794,1.402]}} 
{"id": "9164991066","server": "5507","farm": "6","userId": "70286556@N00","secret": "2da3b4a907","title": "IMG_0677","loc": {"type": "Point","coordinates": [103.79575,1.401922]}} 
{"id": "9162767481","server": "7285","farm": "8","userId": "70286556@N00","secret": "ef5ce130e0","title": "IMG_0678","loc": {"type": "Point","coordinates": [103.79575,1.401922]}} 
{"id": "9162754909","server": "3688","farm": "4","userId": "70286556@N00","secret": "00f3a175bc","title": "IMG_1102","loc": {"type": "Point","coordinates": [103.79412,1.401833]}} 
{"id": "9037191278","server": "2891","farm": "3","userId": "7131703@N03","secret": "9ed26c385b","title": "IMG_2853","loc": {"type": "Point","coordinates": [103.794334,1.401666]}} 
{"id": "9037184674","server": "5350","farm": "6","userId": "7131703@N03","secret": "e1583dfaa2","title": "IMG_2868","loc": {"type": "Point","coordinates": [103.79483,1.402]}} 
{"id": "9034967071","server": "5453","farm": "6","userId": "7131703@N03","secret": "c1db6fb7e7","title": "IMG_2856","loc": {"type": "Point","coordinates": [103.79417,1.401333]}} 
{"id": "9034966727","server": "7444","farm": "8","userId": "7131703@N03","secret": "21104df010","title": "IMG_2857","loc": {"type": "Point","coordinates": [103.79417,1.401333]}} 
{"id": "9034968481","server": "7347","farm": "8","userId": "7131703@N03","secret": "0fe5f00cca","title": "IMG_2852","loc": {"type": "Point","coordinates": [103.794,1.401833]}} 
{"id": "9034961763","server": "3822","farm": "4","userId": "7131703@N03","secret": "0be4125ef3","title": "IMG_2867","loc": {"type": "Point","coordinates": [103.795,1.402]}} 
{"id": "8851381294","server": "2884","farm": "3","userId": "33938770@N05","secret": "014cbeb42c","title": "Giraffe and Man With Carrot, Singapore Zoo","loc": {"type": "Point","coordinates": [103.794,1.401833]}} 
{"id": "8694264927","server": "8119","farm": "9","userId": "91045161@N04","secret": "703337ae59","title": "DSC01031","loc": {"type": "Point","coordinates": [103.79425,1.40213]}} 
{"id": "8695382258","server": "8543","farm": "9","userId": "91045161@N04","secret": "75e89c1397","title": "DSC01038","loc": {"type": "Point","coordinates": [103.79456,1.40148]}} 
{"id": "8695383652","server": "8253","farm": "9","userId": "91045161@N04","secret": "b9a9a111c9","title": "DSC01033","loc": {"type": "Point","coordinates": [103.7941,1.402075]}} 
{"id": "8694265289","server": "8118","farm": "9","userId": "91045161@N04","secret": "3f65932a6f","title": "DSC01030","loc": {"type": "Point","coordinates": [103.79425,1.40215]}} 
{"id": "8694262581","server": "8256","farm": "9","userId": "91045161@N04","secret": "5cdd30dd68","title": "DSC01039","loc": {"type": "Point","coordinates": [103.79456,1.40148]}} 
{"id": "8695383094","server": "8256","farm": "9","userId": "91045161@N04","secret": "ef9a079308","title": "DSC01036","loc": {"type": "Point","coordinates": [103.79427,1.401394]}} 
{"id": "8695381426","server": "8259","farm": "9","userId": "91045161@N04","secret": "9e44691e5a","title": "DSC01040","loc": {"type": "Point","coordinates": [103.79477,1.401658]}} 
{"id": "8695380556","server": "8265","farm": "9","userId": "91045161@N04","secret": "0114517e7f","title": "DSC01043","loc": {"type": "Point","coordinates": [103.79479,1.40168]}} 
{"id": "8694260885","server": "8539","farm": "9","userId": "91045161@N04","secret": "e26dc02e0f","title": "DSC01045","loc": {"type": "Point","coordinates": [103.79482,1.401797]}} 
{"id": "8695385446","server": "8265","farm": "9","userId": "91045161@N04","secret": "68589b1acc","title": "DSC01027","loc": {"type": "Point","coordinates": [103.79397,1.40218]}} 
{"id": "8694261795","server": "8261","farm": "9","userId": "91045161@N04","secret": "a9504861d8","title": "DSC01042","loc": {"type": "Point","coordinates": [103.794685,1.401775]}} 
{"id": "8694264519","server": "8546","farm": "9","userId": "91045161@N04","secret": "ee1142881c","title": "DSC01032","loc": {"type": "Point","coordinates": [103.794655,1.401661]}} 
{"id": "8695382712","server": "8125","farm": "9","userId": "91045161@N04","secret": "25c5f3d0d3","title": "DSC01037","loc": {"type": "Point","coordinates": [103.79429,1.401397]}} 
{"id": "8630491639","server": "8261","farm": "9","userId": "42789083@N00","secret": "d64d8ab675","title": "20130324-6D-100-2562","loc": {"type": "Point","coordinates": [103.79487,1.402086]}} 
{"id": "8482268856","server": "8089","farm": "9","userId": "20390873@N05","secret": "fdb8b34af6","title": "Jaguar","loc": {"type": "Point","coordinates": [103.79494,1.402128]}} 
{"id": "8481174895","server": "8522","farm": "9","userId": "20390873@N05","secret": "7ba3d5b799","title": "Lip licking good","loc": {"type": "Point","coordinates": [103.794914,1.402073]}} 
{"id": "8481171869","server": "8091","farm": "9","userId": "20390873@N05","secret": "c3658ac44a","title": "Jaguar","loc": {"type": "Point","coordinates": [103.79504,1.402122]}} 
{"id": "8459595731","server": "8507","farm": "9","userId": "66358983@N07","secret": "9bb7b244bb","title": "Macaque Family Portrait","loc": {"type": "Point","coordinates": [103.803,1.396999]}} 
{"id": "8351241177","server": "8052","farm": "9","userId": "46275416@N04","secret": "ed48cd42f5","title": "Upper Seletar Reservoir","loc": {"type": "Point","coordinates": [103.80226,1.397506]}} 
{"id": "8350476572","server": "8221","farm": "9","userId": "70108735@N06","secret": "bb676fe55b","title": "The bridge leads to nowhere...","loc": {"type": "Point","coordinates": [103.802086,1.396563]}} 
{"id": "8349894796","server": "8374","farm": "9","userId": "46275416@N04","secret": "1be62e89cc","title": "Upper Seletar Reservoir","loc": {"type": "Point","coordinates": [103.80224,1.397528]}} 
{"id": "8310446744","server": "8212","farm": "9","userId": "88189322@N05","secret": "a91e4f7e6e","title": "2012-10-12 13.08.23","loc": {"type": "Point","coordinates": [103.79782,1.39968]}} 
{"id": "8295307382","server": "8501","farm": "9","userId": "70133597@N07","secret": "d0b262865b","title": "Singapore","loc": {"type": "Point","coordinates": [103.79553,1.402108]}} 
{"id": "8295307016","server": "8354","farm": "9","userId": "70133597@N07","secret": "9a4b8c2449","title": "Singapore","loc": {"type": "Point","coordinates": [103.795044,1.402022]}} 
{"id": "8295307666","server": "8500","farm": "9","userId": "70133597@N07","secret": "97c5cce0ec","title": "Singapore","loc": {"type": "Point","coordinates": [103.79553,1.402108]}} 
{"id": "8294252259","server": "8359","farm": "9","userId": "70133597@N07","secret": "0c84dcdc7e","title": "Singapore","loc": {"type": "Point","coordinates": [103.795044,1.402022]}} 
